kglab/__init__.py
kglab/algebra.py
kglab/decorators.py
kglab/external_import.py
kglab/gpviz.py
kglab/graph.py
kglab/kglab.py
kglab/networks.py
kglab/pkg_types.py
kglab/query/__init__.py
kglab/query/base.py
kglab/query/mixin.py
kglab/query/sparql.py
kglab/serde.py
kglab/standards.py
kglab/subg.py
kglab/topo.py
kglab/util.py
kglab/version.py
kglab-1.0.1.dist-info/METADATA
kglab-1.0.1.dist-info/WHEEL
kglab-1.0.1.dist-info/licenses/LICENSE
kglab-1.0.1.dist-info/RECORD
