Metadata-Version: 2.4
Name: kglab
Version: 1.0.1
Summary: a simple abstraction layer in Python for building knowledge graphs
License-Expression: MIT
License-File: LICENSE
Keywords: cugraph,gpu,graph algorithms,inference,interactive visualization,knowledge graph,managing namespaces,morph-kgc,rdf,rml,validation
Author: Paco Nathan
Author-email: paco@senzing.com
Requires-Python: >=3.11,<3.14
Classifier: Programming Language :: Python
Classifier: Programming Language :: Python :: 3 :: Only
Classifier: Programming Language :: Python :: 3.11
Classifier: Programming Language :: Python :: 3.12
Classifier: Programming Language :: Python :: 3.13
Classifier: Operating System :: OS Independent
Classifier: License :: OSI Approved :: MIT License
Classifier: Development Status :: 5 - Production/Stable
Classifier: Intended Audience :: Developers
Classifier: Intended Audience :: Education
Classifier: Intended Audience :: Information Technology
Classifier: Intended Audience :: Science/Research
Classifier: Topic :: Scientific/Engineering :: Artificial Intelligence
Classifier: Topic :: Scientific/Engineering :: Human Machine Interfaces
Classifier: Topic :: Scientific/Engineering :: Information Analysis
Classifier: Topic :: Software Development :: Libraries :: Python Modules
Classifier: Topic :: Text Processing :: Indexing
Requires-Dist: apeye (>=1.4.1)
Requires-Dist: chocolate (>=0.0.2)
Requires-Dist: cryptography (>=45.0.6)
Requires-Dist: csvwlib (>=0.3.2)
Requires-Dist: decorator (>=5.2.1)
Requires-Dist: gcsfs (>=2025.7.0)
Requires-Dist: icecream (>=2.1.7)
Requires-Dist: igraph (>=0.11.9)
Requires-Dist: jpype1 (>=1.6.0)
Requires-Dist: jupyterlab (>=4.5.1,<5.0.0)
Requires-Dist: jupyterlab-execute-time (>=3.2.0)
Requires-Dist: networkx (>=3.5)
Requires-Dist: nvidia-ml-py (>=13.590.44,<14.0.0)
Requires-Dist: owlrl (>=7.1.4)
Requires-Dist: pyarrow (>=21.0.0)
Requires-Dist: pyjelly[rdflib] (>=0.7.1,<0.8.0)
Requires-Dist: pyshacl (>=0.30.1)
Requires-Dist: python-dateutil (>=2.9.0)
Requires-Dist: pyvis (>=0.3.2)
Requires-Dist: rdflib (>=7.4.0,<8.0.0)
Requires-Dist: requests (>=2.32.5)
Requires-Dist: sqlalchemy (>=2.0.45,<3.0.0)
Requires-Dist: statsmodels (>=0.14.6,<0.15.0)
Requires-Dist: tqdm (>=4.67.1)
Requires-Dist: watermark (>=2.5.0)
Project-URL: Documentation, https://derwen.ai/docs/kgl/
Project-URL: Homepage, https://derwen.ai
Project-URL: Repository, https://github.com/DerwenAI/kglab
